<?xml version="1.0"?>
<!DOCTYPE facelet-taglib PUBLIC
  "-//Sun Microsystems, Inc.//DTD Facelet Taglib 1.0//EN"
  "facelet-taglib_1_0.dtd">
<facelet-taglib>
	<namespace>http://topnet.it/functions</namespace>
	<function>
		<function-name>nl2br</function-name>
		<function-class>it.somaro.web.utils.Util</function-class>
		<function-signature>
			java.lang.String nl2br(java.lang.String)
		</function-signature>
	</function>
	<function>
		<function-name>init</function-name>
		<function-class>
			it.smartflower.web.utils.JSFStatics
		</function-class>
		<function-signature>
			void init(java.lang.String, java.lang.String,java.lang.String)
		</function-signature>
	</function>
	<function>
		<function-name>getContactType</function-name>
		<function-class>it.somaro.web.utils.Util</function-class>
		<function-signature>
			java.lang.String getContactType(java.lang.Integer)
		</function-signature>
	</function>
	<function>
		<function-name>getEntityTypeVisual</function-name>
		<function-class>it.somaro.web.utils.Util</function-class>
		<function-signature>
			java.lang.String getEntityTypeVisual(java.lang.Integer)
		</function-signature>
	</function>
	<function>
		<function-name>getComuniItems2</function-name>
		<function-class>it.somaro.web.utils.Util</function-class>
		<function-signature>
			javax.faces.model.SelectItem[] getComuniItems2(it.somaro.par.Contact)
		</function-signature>
	</function>
	<function>
		<function-name>getComuniItems2T</function-name>
		<function-class>it.somaro.web.utils.Util</function-class>
		<function-signature>
			javax.faces.model.SelectItem[] getComuniItems2T(it.somaro.par.ContactTemp)
		</function-signature>
	</function>
	<function>
		<function-name>getCapItems2</function-name>
		<function-class>it.somaro.web.utils.Util</function-class>
		<function-signature>
			javax.faces.model.SelectItem[] getCapItems2(it.somaro.par.Contact)
		</function-signature>
	</function>
	<function>
		<function-name>getCapItems2T</function-name>
		<function-class>it.somaro.web.utils.Util</function-class>
		<function-signature>
			javax.faces.model.SelectItem[] getCapItems2T(it.somaro.par.ContactTemp)
		</function-signature>
	</function>
	<function>
		<function-name>getComuniItems3</function-name>
		<function-class>it.somaro.web.utils.Util</function-class>
		<function-signature>
			javax.faces.model.SelectItem[] getComuniItems3(it.somaro.par.Operator)
		</function-signature>
	</function>
	<function>
		<function-name>getComuniItems4</function-name>
		<function-class>it.somaro.web.utils.Util</function-class>
		<function-signature>
			javax.faces.model.SelectItem[] getComuniItems4(it.somaro.par.Contact)
		</function-signature>
	</function>
	<function>
		<function-name>getCapItems3</function-name>
		<function-class>it.somaro.web.utils.Util</function-class>
		<function-signature>
			javax.faces.model.SelectItem[] getCapItems3(it.somaro.par.Operator)
		</function-signature>
	</function>
	<function>
		<function-name>getArrayValue</function-name>
		<function-class>it.somaro.web.utils.Util</function-class>
		<function-signature>
			java.lang.String getArrayValue(java.lang.String,java.lang.Long)
		</function-signature>
	</function>

	<function>
		<function-name>getMapValue</function-name>
		<function-class>it.somaro.web.utils.Util</function-class>
		<function-signature>
			java.lang.Object getMapValue(java.lang.String,java.lang.Object)
		</function-signature>
	</function>

	<function>
		<function-name>getMap2Item</function-name>
		<function-class>it.somaro.web.utils.Util</function-class>
		<function-signature>
			javax.faces.model.SelectItem[] getMap2Item(java.lang.String)
		</function-signature>
	</function>

	<function>
		<function-name>shortenNationName</function-name>
		<function-class>it.somaro.web.utils.Util</function-class>
		<function-signature>
			java.lang.String shortenNationName(java.lang.String)
		</function-signature>
	</function>

	<function>
		<function-name>getDnsList</function-name>
		<function-class>it.somaro.web.utils.Util</function-class>
		<function-signature>
			javax.faces.model.SelectItem[] getDnsList(it.somaro.par.Operator)
		</function-signature>
	</function>

	<function>
		<function-name>getDnsIdList</function-name>
		<function-class>it.somaro.web.utils.Util</function-class>
		<function-signature>
			javax.faces.model.SelectItem[] getDnsIdList(it.somaro.par.Operator)
		</function-signature>
	</function>

	<function>
		<function-name>getDns</function-name>
		<function-class>it.somaro.web.utils.Util</function-class>
		<function-signature>
			it.somaro.par.Dns getDns(it.somaro.par.Operator,java.lang.Long)
		</function-signature>
	</function>

	<function>
		<function-name>getArraySubset2Item</function-name>
		<function-class>it.somaro.web.utils.Util</function-class>
		<function-signature>
			javax.faces.model.SelectItem[] getArraySubset2Item(java.lang.String, java.lang.String)
		</function-signature>
	</function>

	<function>
		<function-name>getArray2Item</function-name>
		<function-class>it.somaro.web.utils.Util</function-class>
		<function-signature>
			javax.faces.model.SelectItem[] getArray2Item(java.lang.String)
		</function-signature>
	</function>
	<function>
		<function-name>getCodice</function-name>
		<function-class>
			it.email.pro.web.utils.CodiciUtil
		</function-class>
		<function-signature>
			java.lang.String getCodice(java.lang.Integer)
		</function-signature>
	</function>

	<function>
		<function-name>getComuniItems</function-name>
		<function-class>it.somaro.web.utils.Util</function-class>
		<function-signature>
			javax.faces.model.SelectItem[] getComuniItems(java.lang.String)
		</function-signature>
	</function>
	<function>
		<function-name>getCapItems</function-name>
		<function-class>it.somaro.web.utils.Util</function-class>
		<function-signature>
			javax.faces.model.SelectItem[] getCapItems(java.lang.String)
		</function-signature>
	</function>
	<function>
		<function-name>getRemoteAddr</function-name>
		<function-class>
			it.smartflower.web.utils.JSFUtils
		</function-class>
		<function-signature>
			java.lang.String getRemoteAddr()
		</function-signature>
	</function>
	<function>
		<function-name>init</function-name>
		<function-class>
			it.smartflower.web.utils.JSFStatics
		</function-class>
		<function-signature>
			void init(java.lang.String, java.lang.String, java.lang.String)
		</function-signature>
	</function>
	<function>
		<function-name>isRin</function-name>
		<function-class>
			it.somaro.web.utils.Util
		</function-class>
		<function-signature>
			boolean isRin(it.somaro.par.Domain)
		</function-signature>
	</function>
	<function>
		<function-name>maxRin</function-name>
		<function-class>
			it.somaro.web.utils.Util
		</function-class>
		<function-signature>
			java.util.Date maxRin(it.somaro.par.Domain)
		</function-signature>
	</function>

</facelet-taglib>